<!--
 @title Roller bind value
 @brief Roller bound to a subject; a button jumps it programmatically.

 The roller's `bind_value` is wired to `subject_index`. A "Wednesday" button uses
 `subject_set_int_event` to write `3` into the subject on click — the roller
 picks up the change and animates to that option without any direct call into
 the roller widget.
-->
<screen>
	<view flex_flow="column" style_flex_cross_place="center" style_pad_row="16">
		<!-- 💡 Scroll the roller, or click the button to snap to a fixed option through the subject. -->
		<lv_label width="100%" style_text_align="center" text="Roller: bind to subject" />

		<lv_roller width="160" visible_row_count="3" options="Mon&#10;Tue&#10;Wed&#10;Thu&#10;Fri&#10;Sat&#10;Sun" bind_value="subject_index" />

		<lv_button>
			<lv_label align="center" text="Jump to Wed" />
			<subject_set_int_event subject="subject_index" value="2" />
		</lv_button>
	</view>
</screen>
